{"row": {"author_id": "https://openalex.org/A5079340514", "scopus_id": "57203414476", "h_index": "9", "document_count": "15", "current_affiliation": "", "current_affiliation_country": "", "affiliation_history": "", "updated_at": "2026-05-04T20:23:01+00:00"}, "raw": {"author-retrieval-response": [{"@status": "found", "@_fa": "true", "coredata": {"prism:url": "http://api.elsevier.com/content/author/author_id/57203414476", "dc:identifier": "AUTHOR_ID:57203414476", "historical-identifier": [{"@_fa": "true", "$": "author_id:57016603500"}], "eid": "9-s2.0-57203414476", "orcid": "0000-0002-2822-3869", "document-count": "15", "cited-by-count": "188", "citation-count": "209", "link": [{"@href": "https://www.scopus.com/authid/detail.uri?partnerID=HzOxMe3b&authorId=57203414476&origin=inward", "@rel": "scopus-author", "@_fa": "true"}, {"@href": "http://api.elsevier.com/content/author/author_id/57203414476", "@rel": "self", "@_fa": "true"}, {"@href": "http://api.elsevier.com/content/search/scopus?query=au-id%2857203414476%29", "@rel": "search", "@_fa": "true"}, {"@href": "http://api.elsevier.com/content/search/author?co-author=57203414476", "@rel": "coauthor-search", "@_fa": "true"}]}, "h-index": "9", "coauthor-count": "64", "affiliation-current": {"@id": "104779293", "@href": "http://api.elsevier.com/content/affiliation/affiliation_id/104779293"}, "affiliation-history": {"affiliation": [{"@_fa": "true", "@id": "60070611", "@href": "http://api.elsevier.com/content/affiliation/affiliation_id/60070611"}, {"@_fa": "true", "@id": "125125377", "@href": "http://api.elsevier.com/content/affiliation/affiliation_id/125125377"}, {"@_fa": "true", "@id": "60117839", "@href": "http://api.elsevier.com/content/affiliation/affiliation_id/60117839"}]}, "subject-areas": {"subject-area": [{"@_fa": "true", "@abbrev": "CHEM", "@code": "1605", "$": "Organic Chemistry"}, {"@_fa": "true", "@abbrev": "BIOC", "@code": "1313", "$": "Molecular Medicine"}, {"@_fa": "true", "@abbrev": "MEDI", "@code": "2713", "$": "Epidemiology"}, {"@_fa": "true", "@abbrev": "BIOC", "@code": "1303", "$": "Biochemistry"}, {"@_fa": "true", "@abbrev": "AGRI", "@code": "1105", "$": "Ecology, Evolution, Behavior and Systematics"}, {"@_fa": "true", "@abbrev": "CHEM", "@code": "1602", "$": "Analytical Chemistry"}, {"@_fa": "true", "@abbrev": "AGRI", "@code": "1110", "$": "Plant Science"}, {"@_fa": "true", "@abbrev": "AGRI", "@code": "1100", "$": "Agricultural and Biological Sciences (all)"}, {"@_fa": "true", "@abbrev": "ENVI", "@code": "2303", "$": "Ecology"}, {"@_fa": "true", "@abbrev": "PHAR", "@code": "3002", "$": "Drug Discovery"}, {"@_fa": "true", "@abbrev": "BIOC", "@code": "1300", "$": "Biochemistry, Genetics and Molecular Biology (all)"}, {"@_fa": "true", "@abbrev": "AGRI", "@code": "1102", "$": "Agronomy and Crop Science"}, {"@_fa": "true", "@abbrev": "AGRI", "@code": "1104", "$": "Aquatic Science"}, {"@_fa": "true", "@abbrev": "ENGI", "@code": "2200", "$": "Engineering (all)"}, {"@_fa": "true", "@abbrev": "PHAR", "@code": "3001", "$": "Pharmacology, Toxicology and Pharmaceutics (miscellaneous)"}, {"@_fa": "true", "@abbrev": "CHEM", "@code": "1606", "$": "Physical and Theoretical Chemistry"}, {"@_fa": "true", "@abbrev": "PHAR", "@code": "3003", "$": "Pharmaceutical Science"}, {"@_fa": "true", "@abbrev": "AGRI", "@code": "1111", "$": "Soil Science"}, {"@_fa": "true", "@abbrev": "AGRI", "@code": "1106", "$": "Food Science"}, {"@_fa": "true", "@abbrev": "CHEM", "@code": "1601", "$": "Chemistry (miscellaneous)"}, {"@_fa": "true", "@abbrev": "IMMU", "@code": "2401", "$": "Immunology and Microbiology (miscellaneous)"}, {"@_fa": "true", "@abbrev": "MEDI", "@code": "2700", "$": "Medicine (all)"}, {"@_fa": "true", "@abbrev": "IMMU", "@code": "2403", "$": "Immunology"}, {"@_fa": "true", "@abbrev": "ENVI", "@code": "2304", "$": "Environmental Chemistry"}, {"@_fa": "true", "@abbrev": "MEDI", "@code": "2739", "$": "Public Health, Environmental and Occupational Health"}]}, "author-profile": {"status": "update", "date-created": {"@day": "22", "@month": "08", "@year": "2018"}, "preferred-name": {"@date-locked": "2022-10-06T13:58:10.227-04:00", "@source": "corrapi-external", "initials": "S.", "indexed-name": "Kaleem S.", "surname": "Kaleem", "given-name": "Sidra"}, "classificationgroup": {"classifications": {"@type": "ASJC", "classification": [{"@frequency": "4", "$": "1605"}, {"@frequency": "1", "$": "1313"}, {"@frequency": "1", "$": "2713"}, {"@frequency": "3", "$": "1303"}, {"@frequency": "2", "$": "1105"}, {"@frequency": "2", "$": "1602"}, {"@frequency": "6", "$": "1110"}, {"@frequency": "1", "$": "1100"}, {"@frequency": "2", "$": "2303"}, {"@frequency": "6", "$": "3002"}, {"@frequency": "1", "$": "1300"}, {"@frequency": "2", "$": "1102"}, {"@frequency": "1", "$": "1104"}, {"@frequency": "1", "$": "2200"}, {"@frequency": "3", "$": "3001"}, {"@frequency": "1", "$": "1606"}, {"@frequency": "4", "$": "3003"}, {"@frequency": "1", "$": "1111"}, {"@frequency": "2", "$": "1106"}, {"@frequency": "1", "$": "1601"}, {"@frequency": "1", "$": "2401"}, {"@frequency": "5", "$": "2700"}, {"@frequency": "1", "$": "2403"}, {"@frequency": "1", "$": "2304"}, {"@frequency": "1", "$": "2739"}]}}, "publication-range": {"@end": "2026", "@start": "2015"}, "affiliation-current": {"affiliation": {"@affiliation-id": "104779293", "@parent": "60070611", "@source": "internal-ani", "ip-doc": {"@id": "104779293", "@type": "dept", "@relationship": "author", "afdispname": "Riphah International University, Riphah Institute of Pharmaceutical Sciences", "preferred-name": {"@source": "internal-ani", "$": "Riphah Institute of Pharmaceutical Sciences"}, "parent-preferred-name": {"@source": "internal-ani", "$": "Riphah International University"}, "sort-name": "Riphah Institute of Pharmaceutical Sciences", "address": {"@country": "pak", "address-part": "Sector I-14, Hajj Complex", "city": "Islamabad", "country": "Pakistan"}, "org-domain": "riphah.edu.pk", "org-URL": "https://www.riphah.edu.pk/"}}}, "affiliation-history": {"affiliation": [{"@affiliation-id": "104779293", "@parent": "60070611", "@source": "internal-ani", "ip-doc": {"@id": "104779293", "@type": "dept", "@relationship": "author", "afdispname": "Riphah International University, Riphah Institute of Pharmaceutical Sciences", "preferred-name": {"@source": "internal-ani", "$": "Riphah Institute of Pharmaceutical Sciences"}, "parent-preferred-name": {"@source": "internal-ani", "$": "Riphah International University"}, "sort-name": "Riphah Institute of Pharmaceutical Sciences", "address": {"@country": "pak", "address-part": "Sector I-14, Hajj Complex", "city": "Islamabad", "country": "Pakistan"}, "org-domain": "riphah.edu.pk", "org-URL": "https://www.riphah.edu.pk/"}}, {"@affiliation-id": "128678844", "@parent": "60070611", "@source": "internal-ani", "ip-doc": {"@id": "128678844", "@type": "dept", "@relationship": "author", "afdispname": "Riphah International University, Department of Pharmacy Practice", "preferred-name": {"@source": "internal-ani", "$": "Department of Pharmacy Practice"}, "parent-preferred-name": {"@source": "internal-ani", "$": "Riphah International University"}, "sort-name": "Department of Pharmacy Practice", "address": {"@country": "pak", "address-part": "Sector I-14, Hajj Complex", "city": "Islamabad", "country": "Pakistan"}, "org-domain": "riphah.edu.pk", "org-URL": "https://www.riphah.edu.pk/"}}, {"@affiliation-id": "60070611", "@source": "internal-ani", "ip-doc": {"@id": "60070611", "@type": "parent", "@relationship": "author", "afnameid": "Riphah International University#60070611", "afdispname": "Riphah International University", "preferred-name": {"@source": "internal-ani", "$": "Riphah International University"}, "sort-name": "Riphah International University", "address": {"@country": "pak", "address-part": "Sector I-14, Hajj Complex", "city": "Islamabad", "country": "Pakistan"}, "org-domain": "riphah.edu.pk", "org-URL": "https://www.riphah.edu.pk/"}}, {"@affiliation-id": "125125377", "@source": "internal-ani", "ip-doc": {"@id": "125125377", "@type": "parent", "@relationship": "author", "afnameid": "Riphah Institute of Pharmaceutical Sciences#125125377", "afdispname": "Riphah Institute of Pharmaceutical Sciences", "preferred-name": {"@source": "internal-ani", "$": "Riphah Institute of Pharmaceutical Sciences"}, "sort-name": "Riphah Institute of Pharmaceutical Sciences", "address": {"@country": "pak", "address-part": "F-5/1", "city": "Islamabad", "postal-code": "44600", "country": "Pakistan"}}}, {"@affiliation-id": "60117839", "@source": "internal-ani", "ip-doc": {"@id": "60117839", "@type": "parent", "@relationship": "author", "afnameid": "Ocean College Zhejiang University#60117839", "afdispname": "Ocean College Zhejiang University", "preferred-name": {"@source": "internal-ani", "$": "Ocean College Zhejiang University"}, "sort-name": "Ocean College Zhejiang University", "address": {"@country": "chn", "address-part": "1 Zheda Road", "city": "Zhoushan", "state": "Zhejiang", "postal-code": "316000", "country": "China"}, "org-domain": "oc.zju.edu.cn", "org-URL": "http://oc.zju.edu.cn/global/main.htm"}}, {"@affiliation-id": "122865840", "@parent": "60117839", "@source": "internal-ani", "ip-doc": {"@id": "122865840", "@type": "dept", "@relationship": "author", "afdispname": "Ocean College Zhejiang University, Department of Marine Sciences", "preferred-name": {"@source": "internal-ani", "$": "Department of Marine Sciences"}, "parent-preferred-name": {"@source": "internal-ani", "$": "Ocean College Zhejiang University"}, "sort-name": "Department of Marine Sciences", "address": {"@country": "chn", "address-part": "1 Zheda Road", "city": "Zhoushan", "state": "Zhejiang", "postal-code": "316000", "country": "China"}, "org-domain": "oc.zju.edu.cn", "org-URL": "http://oc.zju.edu.cn/global/main.htm"}}, {"@affiliation-id": "123162399", "@parent": "60117839", "@source": "internal-ani", "ip-doc": {"@id": "123162399", "@type": "dept", "@relationship": "author", "afdispname": "Ocean College Zhejiang University, Zhoushan Campus", "preferred-name": {"@source": "internal-ani", "$": "Zhoushan Campus"}, "parent-preferred-name": {"@source": "internal-ani", "$": "Ocean College Zhejiang University"}, "sort-name": "Zhoushan Campus", "address": {"@country": "chn", "address-part": "1 Zheda Road", "city": "Zhoushan", "state": "Zhejiang", "postal-code": "316000", "country": "China"}, "org-domain": "oc.zju.edu.cn", "org-URL": "http://oc.zju.edu.cn/global/main.htm"}}, {"@affiliation-id": "113733911", "@parent": "60117839", "@source": "internal-ani", "ip-doc": {"@id": "113733911", "@type": "dept", "@relationship": "author", "afdispname": "Zhejiang University, Ocean College", "preferred-name": {"@source": "internal-ani", "$": "Ocean College"}, "parent-preferred-name": {"@source": "internal-ani", "$": "Zhejiang University"}, "sort-name": "Ocean College", "address": {"@country": "chn", "address-part": "Zijingang Campus, 866 Yuhangtang Road", "city": "Hangzhou", "state": "Zhejiang", "postal-code": "310058", "country": "China"}, "org-domain": "zju.edu.cn", "org-URL": "https://www.zju.edu.cn/english/main.htm"}}, {"@affiliation-id": "104729251", "@parent": "60064058", "@source": "internal-ani", "ip-doc": {"@id": "104729251", "@type": "dept", "@relationship": "author", "afdispname": "Quaid-i-Azam University, Department of Microbiology", "preferred-name": {"@source": "internal-ani", "$": "Department of Microbiology"}, "parent-preferred-name": {"@source": "internal-ani", "$": "Quaid-i-Azam University"}, "sort-name": "Department of Microbiology", "address": {"@country": "pak", "address-part": "PO Box 1090", "city": "Islamabad", "state": "Islamabad", "postal-code": "45320", "country": "Pakistan"}, "org-domain": "qau.edu.pk", "org-URL": "https://qau.edu.pk/"}}]}}}]}}