{"row": {"author_id": "https://openalex.org/A5101651289", "scopus_id": "55279286800", "h_index": "21", "document_count": "83", "current_affiliation": "", "current_affiliation_country": "", "affiliation_history": "", "updated_at": "2026-05-04T20:13:49+00:00"}, "raw": {"author-retrieval-response": [{"@status": "found", "@_fa": "true", "coredata": {"prism:url": "http://api.elsevier.com/content/author/author_id/55279286800", "dc:identifier": "AUTHOR_ID:55279286800", "eid": "9-s2.0-55279286800", "orcid": "0000-0002-5748-6473", "document-count": "83", "cited-by-count": "995", "citation-count": "1333", "link": [{"@href": "https://www.scopus.com/authid/detail.uri?partnerID=HzOxMe3b&authorId=55279286800&origin=inward", "@rel": "scopus-author", "@_fa": "true"}, {"@href": "http://api.elsevier.com/content/author/author_id/55279286800", "@rel": "self", "@_fa": "true"}, {"@href": "http://api.elsevier.com/content/search/scopus?query=au-id%2855279286800%29", "@rel": "search", "@_fa": "true"}, {"@href": "http://api.elsevier.com/content/search/author?co-author=55279286800", "@rel": "coauthor-search", "@_fa": "true"}]}, "h-index": "21", "coauthor-count": "237", "affiliation-current": {"@id": "131845610", "@href": "http://api.elsevier.com/content/affiliation/affiliation_id/131845610"}, "affiliation-history": {"affiliation": [{"@_fa": "true", "@id": "60030274", "@href": "http://api.elsevier.com/content/affiliation/affiliation_id/60030274"}, {"@_fa": "true", "@id": "117055687", "@href": "http://api.elsevier.com/content/affiliation/affiliation_id/117055687"}, {"@_fa": "true", "@id": "113782428", "@href": "http://api.elsevier.com/content/affiliation/affiliation_id/113782428"}]}, "subject-areas": {"subject-area": [{"@_fa": "true", "@abbrev": "MATE", "@code": "2504", "$": "Electronic, Optical and Magnetic Materials"}, {"@_fa": "true", "@abbrev": "ENGI", "@code": "2205", "$": "Civil and Structural Engineering"}, {"@_fa": "true", "@abbrev": "CHEM", "@code": "1602", "$": "Analytical Chemistry"}, {"@_fa": "true", "@abbrev": "ENGI", "@code": "2215", "$": "Building and Construction"}, {"@_fa": "true", "@abbrev": "CHEM", "@code": "1605", "$": "Organic Chemistry"}, {"@_fa": "true", "@abbrev": "COMP", "@code": "1700", "$": "Computer Science (all)"}, {"@_fa": "true", "@abbrev": "PHAR", "@code": "3002", "$": "Drug Discovery"}, {"@_fa": "true", "@abbrev": "CENG", "@code": "1502", "$": "Bioengineering"}, {"@_fa": "true", "@abbrev": "BIOC", "@code": "1304", "$": "Biophysics"}, {"@_fa": "true", "@abbrev": "IMMU", "@code": "2406", "$": "Virology"}, {"@_fa": "true", "@abbrev": "MEDI", "@code": "2726", "$": "Microbiology (medical)"}, {"@_fa": "true", "@abbrev": "MATE", "@code": "2501", "$": "Materials Science (miscellaneous)"}, {"@_fa": "true", "@abbrev": "CHEM", "@code": "1606", "$": "Physical and Theoretical Chemistry"}, {"@_fa": "true", "@abbrev": "ENGI", "@code": "2208", "$": "Electrical and Electronic Engineering"}, {"@_fa": "true", "@abbrev": "AGRI", "@code": "1109", "$": "Insect Science"}, {"@_fa": "true", "@abbrev": "AGRI", "@code": "1102", "$": "Agronomy and Crop Science"}, {"@_fa": "true", "@abbrev": "BIOC", "@code": "1311", "$": "Genetics"}, {"@_fa": "true", "@abbrev": "CHEM", "@code": "1603", "$": "Electrochemistry"}, {"@_fa": "true", "@abbrev": "ENER", "@code": "2105", "$": "Renewable Energy, Sustainability and the Environment"}, {"@_fa": "true", "@abbrev": "ENVI", "@code": "2303", "$": "Ecology"}, {"@_fa": "true", "@abbrev": "AGRI", "@code": "1106", "$": "Food Science"}, {"@_fa": "true", "@abbrev": "ENGI", "@code": "2209", "$": "Industrial and Manufacturing Engineering"}, {"@_fa": "true", "@abbrev": "MATE", "@code": "2500", "$": "Materials Science (all)"}, {"@_fa": "true", "@abbrev": "AGRI", "@code": "1110", "$": "Plant Science"}, {"@_fa": "true", "@abbrev": "BIOC", "@code": "1315", "$": "Structural Biology"}, {"@_fa": "true", "@abbrev": "MATE", "@code": "2507", "$": "Polymers and Plastics"}, {"@_fa": "true", "@abbrev": "MATH", "@code": "2611", "$": "Modeling and Simulation"}, {"@_fa": "true", "@abbrev": "BIOC", "@code": "1308", "$": "Clinical Biochemistry"}, {"@_fa": "true", "@abbrev": "CHEM", "@code": "1604", "$": "Inorganic Chemistry"}, {"@_fa": "true", "@abbrev": "ENGI", "@code": "2210", "$": "Mechanical Engineering"}, {"@_fa": "true", "@abbrev": "BIOC", "@code": "1305", "$": "Biotechnology"}, {"@_fa": "true", "@abbrev": "CENG", "@code": "1503", "$": "Catalysis"}, {"@_fa": "true", "@abbrev": "ENVI", "@code": "2307", "$": "Health, Toxicology and Mutagenesis"}, {"@_fa": "true", "@abbrev": "MEDI", "@code": "2700", "$": "Medicine (all)"}, {"@_fa": "true", "@abbrev": "CENG", "@code": "1500", "$": "Chemical Engineering (all)"}, {"@_fa": "true", "@abbrev": "ENER", "@code": "2102", "$": "Energy Engineering and Power Technology"}, {"@_fa": "true", "@abbrev": "IMMU", "@code": "2404", "$": "Microbiology"}, {"@_fa": "true", "@abbrev": "BIOC", "@code": "1312", "$": "Molecular Biology"}, {"@_fa": "true", "@abbrev": "AGRI", "@code": "1100", "$": "Agricultural and Biological Sciences (all)"}, {"@_fa": "true", "@abbrev": "ENVI", "@code": "2310", "$": "Pollution"}, {"@_fa": "true", "@abbrev": "ENVI", "@code": "2305", "$": "Environmental Engineering"}, {"@_fa": "true", "@abbrev": "ENER", "@code": "2100", "$": "Energy (all)"}, {"@_fa": "true", "@abbrev": "PHYS", "@code": "3104", "$": "Condensed Matter Physics"}, {"@_fa": "true", "@abbrev": "PHAR", "@code": "3003", "$": "Pharmaceutical Science"}, {"@_fa": "true", "@abbrev": "MATE", "@code": "2505", "$": "Materials Chemistry"}, {"@_fa": "true", "@abbrev": "CHEM", "@code": "1600", "$": "Chemistry (all)"}, {"@_fa": "true", "@abbrev": "AGRI", "@code": "1101", "$": "Agricultural and Biological Sciences (miscellaneous)"}, {"@_fa": "true", "@abbrev": "CHEM", "@code": "1601", "$": "Chemistry (miscellaneous)"}, {"@_fa": "true", "@abbrev": "ENVI", "@code": "2308", "$": "Management, Monitoring, Policy and Law"}, {"@_fa": "true", "@abbrev": "CENG", "@code": "1508", "$": "Process Chemistry and Technology"}, {"@_fa": "true", "@abbrev": "BIOC", "@code": "1303", "$": "Biochemistry"}, {"@_fa": "true", "@abbrev": "ENER", "@code": "2103", "$": "Fuel Technology"}, {"@_fa": "true", "@abbrev": "BIOC", "@code": "1313", "$": "Molecular Medicine"}, {"@_fa": "true", "@abbrev": "AGRI", "@code": "1105", "$": "Ecology, Evolution, Behavior and Systematics"}, {"@_fa": "true", "@abbrev": "PHAR", "@code": "3000", "$": "Pharmacology, Toxicology and Pharmaceutics (all)"}, {"@_fa": "true", "@abbrev": "MATE", "@code": "2502", "$": "Biomaterials"}, {"@_fa": "true", "@abbrev": "ENGI", "@code": "2200", "$": "Engineering (all)"}]}, "author-profile": {"status": "update", "date-created": {"@day": "13", "@month": "07", "@year": "2012"}, "preferred-name": {"@date-locked": "2023-12-19T01:09:23.045-05:00", "@source": "corrapi-external", "initials": "X.", "indexed-name": "Hua X.", "surname": "Hua", "given-name": "Xuewen"}, "name-variant": [{"@doc-count": "1", "@source": "internal-ani", "initials": "X.", "indexed-name": "Hua X.", "surname": "Hua", "given-name": "X."}, {"@doc-count": "30", "@source": "internal-ani", "initials": "X.W.", "indexed-name": "Hua X.", "surname": "Hua", "given-name": "Xue Wen"}], "classificationgroup": {"classifications": {"@type": "ASJC", "classification": [{"@frequency": "1", "$": "2504"}, {"@frequency": "1", "$": "2205"}, {"@frequency": "3", "$": "1602"}, {"@frequency": "1", "$": "2215"}, {"@frequency": "15", "$": "1605"}, {"@frequency": "1", "$": "1700"}, {"@frequency": "6", "$": "3002"}, {"@frequency": "1", "$": "1502"}, {"@frequency": "1", "$": "1304"}, {"@frequency": "5", "$": "2406"}, {"@frequency": "5", "$": "2726"}, {"@frequency": "1", "$": "2501"}, {"@frequency": "2", "$": "1606"}, {"@frequency": "1", "$": "2208"}, {"@frequency": "5", "$": "1109"}, {"@frequency": "8", "$": "1102"}, {"@frequency": "2", "$": "1311"}, {"@frequency": "1", "$": "1603"}, {"@frequency": "1", "$": "2105"}, {"@frequency": "1", "$": "2303"}, {"@frequency": "2", "$": "1106"}, {"@frequency": "1", "$": "2209"}, {"@frequency": "1", "$": "2500"}, {"@frequency": "2", "$": "1110"}, {"@frequency": "1", "$": "1315"}, {"@frequency": "1", "$": "2507"}, {"@frequency": "1", "$": "2611"}, {"@frequency": "2", "$": "1308"}, {"@frequency": "1", "$": "1604"}, {"@frequency": "1", "$": "2210"}, {"@frequency": "1", "$": "1305"}, {"@frequency": "1", "$": "1503"}, {"@frequency": "2", "$": "2307"}, {"@frequency": "27", "$": "2700"}, {"@frequency": "2", "$": "1500"}, {"@frequency": "2", "$": "2102"}, {"@frequency": "5", "$": "2404"}, {"@frequency": "3", "$": "1312"}, {"@frequency": "16", "$": "1100"}, {"@frequency": "1", "$": "2310"}, {"@frequency": "1", "$": "2305"}, {"@frequency": "1", "$": "2100"}, {"@frequency": "1", "$": "3104"}, {"@frequency": "6", "$": "3003"}, {"@frequency": "1", "$": "2505"}, {"@frequency": "45", "$": "1600"}, {"@frequency": "1", "$": "1101"}, {"@frequency": "3", "$": "1601"}, {"@frequency": "1", "$": "2308"}, {"@frequency": "1", "$": "1508"}, {"@frequency": "4", "$": "1303"}, {"@frequency": "1", "$": "2103"}, {"@frequency": "5", "$": "1313"}, {"@frequency": "1", "$": "1105"}, {"@frequency": "1", "$": "3000"}, {"@frequency": "3", "$": "2502"}, {"@frequency": "1", "$": "2200"}]}}, "publication-range": {"@end": "2026", "@start": "2012"}, "affiliation-current": {"affiliation": {"@affiliation-id": "131845610", "@parent": "60030274", "@source": "internal-ani", "ip-doc": {"@id": "131845610", "@type": "dept", "@relationship": "author", "afdispname": "Liaocheng University, College of Agriculture and Biology", "preferred-name": {"@source": "internal-ani", "$": "College of Agriculture and Biology"}, "parent-preferred-name": {"@source": "internal-ani", "$": "Liaocheng University"}, "sort-name": "College of Agriculture and Biology", "address": {"@country": "chn", "address-part": "No. 1 Hunan Road", "city": "Liaocheng", "state": "Shandong", "postal-code": "252000", "country": "China"}, "org-domain": "lcu.edu.cn", "org-URL": "https://www.lcu.edu.cn/"}}}, "affiliation-history": {"affiliation": [{"@affiliation-id": "131845610", "@parent": "60030274", "@source": "internal-ani", "ip-doc": {"@id": "131845610", "@type": "dept", "@relationship": "author", "afdispname": "Liaocheng University, College of Agriculture and Biology", "preferred-name": {"@source": "internal-ani", "$": "College of Agriculture and Biology"}, "parent-preferred-name": {"@source": "internal-ani", "$": "Liaocheng University"}, "sort-name": "College of Agriculture and Biology", "address": {"@country": "chn", "address-part": "No. 1 Hunan Road", "city": "Liaocheng", "state": "Shandong", "postal-code": "252000", "country": "China"}, "org-domain": "lcu.edu.cn", "org-URL": "https://www.lcu.edu.cn/"}}, {"@affiliation-id": "104529897", "@parent": "60030274", "@source": "internal-ani", "ip-doc": {"@id": "104529897", "@type": "dept", "@relationship": "author", "afdispname": "Liaocheng University, College of Agriculture", "preferred-name": {"@source": "internal-ani", "$": "College of Agriculture"}, "parent-preferred-name": {"@source": "internal-ani", "$": "Liaocheng University"}, "sort-name": "College of Agriculture", "address": {"@country": "chn", "address-part": "No. 1 Hunan Road", "city": "Liaocheng", "state": "Shandong", "postal-code": "252000", "country": "China"}, "org-domain": "lcu.edu.cn", "org-URL": "https://www.lcu.edu.cn/"}}, {"@affiliation-id": "104529905", "@parent": "60030274", "@source": "internal-ani", "ip-doc": {"@id": "104529905", "@type": "dept", "@relationship": "author", "afdispname": "Liaocheng University, College of Agronomy", "preferred-name": {"@source": "internal-ani", "$": "College of Agronomy"}, "parent-preferred-name": {"@source": "internal-ani", "$": "Liaocheng University"}, "sort-name": "College of Agronomy", "address": {"@country": "chn", "address-part": "No. 1 Hunan Road", "city": "Liaocheng", "state": "Shandong", "postal-code": "252000", "country": "China"}, "org-domain": "lcu.edu.cn", "org-URL": "https://www.lcu.edu.cn/"}}, {"@affiliation-id": "127994930", "@parent": "60030274", "@source": "internal-ani", "ip-doc": {"@id": "127994930", "@type": "dept", "@relationship": "author", "afdispname": "Liaocheng University, College of Agronomy and Agricultural Engineering", "preferred-name": {"@source": "internal-ani", "$": "College of Agronomy and Agricultural Engineering"}, "parent-preferred-name": {"@source": "internal-ani", "$": "Liaocheng University"}, "sort-name": "College of Agronomy and Agricultural Engineering", "address": {"@country": "chn", "address-part": "No. 1 Hunan Road", "city": "Liaocheng", "state": "Shandong", "postal-code": "252000", "country": "China"}, "org-domain": "lcu.edu.cn", "org-URL": "https://www.lcu.edu.cn/"}}, {"@affiliation-id": "104529918", "@parent": "60030274", "@source": "internal-ani", "ip-doc": {"@id": "104529918", "@type": "dept", "@relationship": "author", "afdispname": "Liaocheng University, School of Agricultural Science and Engineering", "preferred-name": {"@source": "internal-ani", "$": "School of Agricultural Science and Engineering"}, "parent-preferred-name": {"@source": "internal-ani", "$": "Liaocheng University"}, "sort-name": "School of Agricultural Science and Engineering", "address": {"@country": "chn", "address-part": "No. 1 Hunan Road", "city": "Liaocheng", "state": "Shandong", "postal-code": "252000", "country": "China"}, "org-domain": "lcu.edu.cn", "org-URL": "https://www.lcu.edu.cn/"}}, {"@affiliation-id": "60030274", "@source": "internal-ani", "ip-doc": {"@id": "60030274", "@type": "parent", "@relationship": "author", "afnameid": "Liaocheng University#60030274", "afdispname": "Liaocheng University", "preferred-name": {"@source": "internal-ani", "$": "Liaocheng University"}, "sort-name": "Liaocheng University", "address": {"@country": "chn", "address-part": "No. 1 Hunan Road", "city": "Liaocheng", "state": "Shandong", "postal-code": "252000", "country": "China"}, "org-domain": "lcu.edu.cn", "org-URL": "https://www.lcu.edu.cn/"}}, {"@affiliation-id": "116889454", "@parent": "60030274", "@source": "internal-ani", "ip-doc": {"@id": "116889454", "@type": "dept", "@relationship": "author", "afdispname": "Liaocheng University, Institute of Biopharmaceutical Research", "preferred-name": {"@source": "internal-ani", "$": "Institute of Biopharmaceutical Research"}, "parent-preferred-name": {"@source": "internal-ani", "$": "Liaocheng University"}, "sort-name": "Institute of Biopharmaceutical Research", "address": {"@country": "chn", "address-part": "No. 1 Hunan Road", "city": "Liaocheng", "state": "Shandong", "postal-code": "252000", "country": "China"}, "org-domain": "lcu.edu.cn", "org-URL": "https://www.lcu.edu.cn/"}}, {"@affiliation-id": "103926108", "@parent": "60018038", "@source": "internal-ani", "ip-doc": {"@id": "103926108", "@type": "dept", "@relationship": "author", "afdispname": "Nankai University, State Key Laboratory of Elemento-Organic Chemistry", "preferred-name": {"@source": "internal-ani", "$": "State Key Laboratory of Elemento-Organic Chemistry"}, "parent-preferred-name": {"@source": "internal-ani", "$": "Nankai University"}, "sort-name": "State Key Laboratory of Elemento-Organic Chemistry", "address": {"@country": "chn", "address-part": "38 Tongyan Road", "city": "Tianjin", "postal-code": "300350", "country": "China"}, "org-domain": "en.nankai.edu.cn", "org-URL": "https://en.nankai.edu.cn/"}}, {"@affiliation-id": "114174832", "@parent": "60030274", "@source": "internal-ani", "ip-doc": {"@id": "114174832", "@type": "dept", "@relationship": "author", "afdispname": "Liaocheng University, School of Pharmacy", "preferred-name": {"@source": "internal-ani", "$": "School of Pharmacy"}, "parent-preferred-name": {"@source": "internal-ani", "$": "Liaocheng University"}, "sort-name": "School of Pharmacy", "address": {"@country": "chn", "address-part": "No. 1 Hunan Road", "city": "Liaocheng", "state": "Shandong", "postal-code": "252000", "country": "China"}, "org-domain": "lcu.edu.cn", "org-URL": "https://www.lcu.edu.cn/"}}, {"@affiliation-id": "117055687", "@source": "internal-ani", "ip-doc": {"@id": "117055687", "@type": "parent", "@relationship": "author", "afnameid": "Shandong Yanhai Construction Resources Co. Ltd#117055687", "afdispname": "Shandong Yanhai Construction Resources Co. Ltd", "preferred-name": {"@source": "internal-ani", "$": "Shandong Yanhai Construction Resources Co. Ltd"}, "sort-name": "Shandong Yanhai Construction Resources Co. Ltd", "address": {"@country": "chn", "address-part": "No. 3-8 Kaifeng Road, Yantai, Shandong, 264006 China", "city": "Yantai", "state": "Shandong", "postal-code": "264006", "country": "China"}}}, {"@affiliation-id": "114160248", "@parent": "60018038", "@source": "internal-ani", "ip-doc": {"@id": "114160248", "@type": "dept", "@relationship": "author", "afdispname": "Nankai University, Collaborative Innovation Center of Chemical Science and Engineering (Tianjin)", "preferred-name": {"@source": "internal-ani", "$": "Collaborative Innovation Center of Chemical Science and Engineering (Tianjin)"}, "parent-preferred-name": {"@source": "internal-ani", "$": "Nankai University"}, "sort-name": "Collaborative Innovation Center of Chemical Science and Engineering (Tianjin)", "address": {"@country": "chn", "address-part": "38 Tongyan Road", "city": "Tianjin", "postal-code": "300350", "country": "China"}, "org-domain": "en.nankai.edu.cn", "org-URL": "https://en.nankai.edu.cn/"}}, {"@affiliation-id": "113782428", "@source": "internal-ani", "ip-doc": {"@id": "113782428", "@type": "parent", "@relationship": "author", "afnameid": "Collaborative Innovation Center of Chemical Science and Engineering (Tianjin)#113782428", "afdispname": "Collaborative Innovation Center of Chemical Science and Engineering (Tianjin)", "preferred-name": {"@source": "internal-ani", "$": "Collaborative Innovation Center of Chemical Science and Engineering (Tianjin)"}, "sort-name": "Collaborative Innovation Center of Chemical Science and Engineering (Tianjin)", "address": {"@country": "chn", "address-part": "Tianjin, 300072 China", "city": "Tianjin", "state": "Tianjin", "postal-code": "300071", "country": "China"}}}]}}}]}}